fastapi_logs/__init__.py
fastapi_logs-0.0.0.dist-info/LICENSE
fastapi_logs-0.0.0.dist-info/METADATA
fastapi_logs-0.0.0.dist-info/WHEEL
fastapi_logs-0.0.0.dist-info/top_level.txt
fastapi_logs-0.0.0.dist-info/RECORD
