Metadata-Version: 2.1
Name: fastapi-logs
Version: 0.0.0
Summary: In development.
Author: Cyberbolt
Author-email: dtconlyone@gmail.com
Classifier: Programming Language :: Python :: 3
Classifier: License :: OSI Approved :: MIT License
Classifier: Operating System :: OS Independent
License-File: LICENSE
Requires-Dist: fastapi
